colouringmap/__init__.py
colouringmap/breaking_levels.py
colouringmap/get_colours.py
colouringmap/mapping_point.py
colouringmap/mapping_polygon.py
colouringmap/mapping_utility.py
colouringmap/markerset.py
colouringmap/theme_mapping.py
colouringmap/fonts/GenJyuuGothicL-P-Normal.ttf
colouringmap/fonts/__init__.py
colouringmap/icons/__init__.py
colouringmap/icons/brandico.ttf
colouringmap/icons/elusive.ttf
colouringmap/icons/entypo.ttf
colouringmap/icons/fontawesome.ttf
colouringmap/icons/fontelico.ttf
colouringmap/icons/icon_map.txt
colouringmap/icons/iconic.ttf
colouringmap/icons/icons_licenses.txt
colouringmap/icons/linecons.ttf
colouringmap/icons/maki.ttf
colouringmap/icons/meteocons.ttf
colouringmap/icons/modernpics.ttf
colouringmap/icons/typicons.ttf
colouringmap/icons/weathercons.ttf
colouringmap/icons/zocial.ttf
colouringmap-0.0.3.dist-info/DESCRIPTION.rst
colouringmap-0.0.3.dist-info/METADATA
colouringmap-0.0.3.dist-info/RECORD
colouringmap-0.0.3.dist-info/WHEEL
colouringmap-0.0.3.dist-info/metadata.json
colouringmap-0.0.3.dist-info/top_level.txt
