Metadata-Version: 2.0
Name: colouringmap
Version: 0.0.3
Summary: a mapping tool for generating choropleth map from map data (shpfile), by breaking sequential values into groups, or beforehand prepared category/level.
Home-page: https://github.com/wcchin/colouringmap
Author: Benny Chin
Author-email: wcchin.88@gmail.com
License: LICENSE.txt
Keywords: map,geography,catography,thematic map
Platform: UNKNOWN
Classifier: Development Status :: 3 - Alpha
Classifier: Intended Audience :: Science/Research
Classifier: Intended Audience :: Education
Classifier: Topic :: Scientific/Engineering :: GIS
Classifier: Topic :: Scientific/Engineering :: Visualization
Classifier: License :: OSI Approved :: MIT License
Classifier: Programming Language :: Python :: 2.7
Requires-Dist: descartes
Requires-Dist: geopandas
Requires-Dist: jenkspy
Requires-Dist: matplotlib-scalebar
Requires-Dist: numpy
Requires-Dist: palettable
